[{"speciesCode": "amekes", "comName": "American Kestrel", "sciName": "Falco sparverius", "locId": "L29077117", "locName": "Everett McKinley Dirksen Memorial Highway, Fithian, Illinois, US (40.121, -87.928)", "obsDt": "2025-12-23 14:20", "howMany": 1, "lat": 40.1214433, "lng": -87.9284053, "obsValid": true, "obsReviewed": false, "locationPrivate": true, "subId": "S289884542"}, {"speciesCode": "cangoo", "comName": "Canada Goose", "sciName": "Branta canadensis", "locId": "L45603025", "locName": "16979 E County Road 2705 N, Danville US-IL 40.25767, -87.62384", "obsDt": "2025-12-23 08:38", "howMany": 240, "lat": 40.257667, "lng": -87.623838, "obsValid": true, "obsReviewed": false, "locationPrivate": true, "subId": "S289858030"}, {"speciesCode": "norsho", "comName": "Northern Shoveler", "sciName": "Spatula clypeata", "locId": "L45603025", "locName": "16979 E County Road 2705 N, Danville US-IL 40.25767, -87.62384", "obsDt": "2025-12-23 08:38", "howMany": 1, "lat": 40.257667, "lng": -87.623838, "obsValid": true, "obsReviewed": false, "locationPrivate": true, "subId": "S289858030"}, {"speciesCode": "rocpig", "comName": "Rock Pigeon", "sciName": "Columba livia", "locId": "L45603025", "locName": "16979 E County Road 2705 N, Danville US-IL 40.25767, -87.62384", "obsDt": "2025-12-23 08:38", "howMany": 1, "lat": 40.257667, "lng": -87.623838, "obsValid": true, "obsReviewed": false, "locationPrivate": true, "subId": "S289858030", "exoticCategory": "N"}, {"speciesCode": "moudov", "comName": "Mourning Dove", "sciName": "Zenaida macroura", "locId": "L45603025", "locName": "16979 E County Road 2705 N, Danville US-IL 40.25767, -87.62384", "obsDt": "2025-12-23 08:38", "howMany": 4, "lat": 40.257667, "lng": -87.623838, "obsValid": true, "obsReviewed": false, "locationPrivate": true, "subId": "S289858030"}, {"speciesCode": "comloo", "comName": "Common Loon", "sciName": "Gavia immer", "locId": "L45603025", "locName": "16979 E County Road 2705 N, Danville US-IL 40.25767, -87.62384", "obsDt": "2025-12-23 08:38", "howMany": 2, "lat": 40.257667, "lng": -87.623838, "obsValid": true, "obsReviewed": false, "locationPrivate": true, "subId": "S289858030"}, {"speciesCode": "turvul", "comName": "Turkey Vulture", "sciName": "Cathartes aura", "locId": "L45603025", "locName": "16979 E County Road 2705 N, Danville US-IL 40.25767, -87.62384", "obsDt": "2025-12-23 08:38", "howMany": 2, "lat": 40.257667, "lng": -87.623838, "obsValid": true, "obsReviewed": false, "locationPrivate": true, "subId": "S289858030"}, {"speciesCode": "reshaw", "comName": "Red-shouldered Hawk", "sciName": "Buteo lineatus", "locId": "L45603025", "locName": "16979 E County Road 2705 N, Danville US-IL 40.25767, -87.62384", "obsDt": "2025-12-23 08:38", "howMany": 2, "lat": 40.257667, "lng": -87.623838, "obsValid": true, "obsReviewed": false, "locationPrivate": true, "subId": "S289858030"}, {"speciesCode": "rebwoo", "comName": "Red-bellied Woodpecker", "sciName": "Melanerpes carolinus", "locId": "L45603025", "locName": "16979 E County Road 2705 N, Danville US-IL 40.25767, -87.62384", "obsDt": "2025-12-23 08:38", "howMany": 3, "lat": 40.257667, "lng": -87.623838, "obsValid": true, "obsReviewed": false, "locationPrivate": true, "subId": "S289858030"}, {"speciesCode": "dowwoo", "comName": "Downy Woodpecker", "sciName": "Dryobates pubescens", "locId": "L45603025", "locName": "16979 E County Road 2705 N, Danville US-IL 40.25767, -87.62384", "obsDt": "2025-12-23 08:38", "howMany": 5, "lat": 40.257667, "lng": -87.623838, "obsValid": true, "obsReviewed": false, "locationPrivate": true, "subId": "S289858030"}, {"speciesCode": "haiwoo", "comName": "Hairy Woodpecker", "sciName": "Leuconotopicus villosus", "locId": "L45603025", "locName": "16979 E County Road 2705 N, Danville US-IL 40.25767, -87.62384", "obsDt": "2025-12-23 08:38", "howMany": 2, "lat": 40.257667, "lng": -87.623838, "obsValid": true, "obsReviewed": false, "locationPrivate": true, "subId": "S289858030"}, {"speciesCode": "pilwoo", "comName": "Pileated Woodpecker", "sciName": "Dryocopus pileatus", "locId": "L45603025", "locName": "16979 E County Road 2705 N, Danville US-IL 40.25767, -87.62384", "obsDt": "2025-12-23 08:38", "howMany": 1, "lat": 40.257667, "lng": -87.623838, "obsValid": true, "obsReviewed": false, "locationPrivate": true, "subId": "S289858030"}, {"speciesCode": "norfli", "comName": "Northern Flicker", "sciName": "Colaptes auratus", "locId": "L45603025", "locName": "16979 E County Road 2705 N, Danville US-IL 40.25767, -87.62384", "obsDt": "2025-12-23 08:38", "howMany": 1, "lat": 40.257667, "lng": -87.623838, "obsValid": true, "obsReviewed": false, "locationPrivate": true, "subId": "S289858030"}, {"speciesCode": "blujay", "comName": "Blue Jay", "sciName": "Cyanocitta cristata", "locId": "L45603025", "locName": "16979 E County Road 2705 N, Danville US-IL 40.25767, -87.62384", "obsDt": "2025-12-23 08:38", "howMany": 5, "lat": 40.257667, "lng": -87.623838, "obsValid": true, "obsReviewed": false, "locationPrivate": true, "subId": "S289858030"}, {"speciesCode": "amecro", "comName": "American Crow", "sciName": "Corvus brachyrhynchos", "locId": "L45603025", "locName": "16979 E County Road 2705 N, Danville US-IL 40.25767, -87.62384", "obsDt": "2025-12-23 08:38", "howMany": 2, "lat": 40.257667, "lng": -87.623838, "obsValid": true, "obsReviewed": false, "locationPrivate": true, "subId": "S289858030"}, {"speciesCode": "carchi", "comName": "Carolina Chickadee", "sciName": "Poecile carolinensis", "locId": "L45603025", "locName": "16979 E County Road 2705 N, Danville US-IL 40.25767, -87.62384", "obsDt": "2025-12-23 08:38", "howMany": 8, "lat": 40.257667, "lng": -87.623838, "obsValid": true, "obsReviewed": false, "locationPrivate": true, "subId": "S289858030"}, {"speciesCode": "tuftit", "comName": "Tufted Titmouse", "sciName": "Baeolophus bicolor", "locId": "L45603025", "locName": "16979 E County Road 2705 N, Danville US-IL 40.25767, -87.62384", "obsDt": "2025-12-23 08:38", "howMany": 4, "lat": 40.257667, "lng": -87.623838, "obsValid": true, "obsReviewed": false, "locationPrivate": true, "subId": "S289858030"}, {"speciesCode": "gockin", "comName": "Golden-crowned Kinglet", "sciName": "Regulus satrapa", "locId": "L45603025", "locName": "16979 E County Road 2705 N, Danville US-IL 40.25767, -87.62384", "obsDt": "2025-12-23 08:38", "howMany": 2, "lat": 40.257667, "lng": -87.623838, "obsValid": true, "obsReviewed": false, "locationPrivate": true, "subId": "S289858030"}, {"speciesCode": "whbnut", "comName": "White-breasted Nuthatch", "sciName": "Sitta carolinensis", "locId": "L45603025", "locName": "16979 E County Road 2705 N, Danville US-IL 40.25767, -87.62384", "obsDt": "2025-12-23 08:38", "howMany": 4, "lat": 40.257667, "lng": -87.623838, "obsValid": true, "obsReviewed": false, "locationPrivate": true, "subId": "S289858030"}, {"speciesCode": "rebnut", "comName": "Red-breasted Nuthatch", "sciName": "Sitta canadensis", "locId": "L45603025", "locName": "16979 E County Road 2705 N, Danville US-IL 40.25767, -87.62384", "obsDt": "2025-12-23 08:38", "howMany": 2, "lat": 40.257667, "lng": -87.623838, "obsValid": true, "obsReviewed": false, "locationPrivate": true, "subId": "S289858030"}, {"speciesCode": "brncre", "comName": "Brown Creeper", "sciName": "Certhia americana", "locId": "L45603025", "locName": "16979 E County Road 2705 N, Danville US-IL 40.25767, -87.62384", "obsDt": "2025-12-23 08:38", "howMany": 1, "lat": 40.257667, "lng": -87.623838, "obsValid": true, "obsReviewed": false, "locationPrivate": true, "subId": "S289858030"}, {"speciesCode": "carwre", "comName": "Carolina Wren", "sciName": "Thryothorus ludovicianus", "locId": "L45603025", "locName": "16979 E County Road 2705 N, Danville US-IL 40.25767, -87.62384", "obsDt": "2025-12-23 08:38", "howMany": 2, "lat": 40.257667, "lng": -87.623838, "obsValid": true, "obsReviewed": false, "locationPrivate": true, "subId": "S289858030"}, {"speciesCode": "eursta", "comName": "European Starling", "sciName": "Sturnus vulgaris", "locId": "L45603025", "locName": "16979 E County Road 2705 N, Danville US-IL 40.25767, -87.62384", "obsDt": "2025-12-23 08:38", "howMany": 36, "lat": 40.257667, "lng": -87.623838, "obsValid": true, "obsReviewed": false, "locationPrivate": true, "subId": "S289858030", "exoticCategory": "N"}, {"speciesCode": "brnthr", "comName": "Brown Thrasher", "sciName": "Toxostoma rufum", "locId": "L45603025", "locName": "16979 E County Road 2705 N, Danville US-IL 40.25767, -87.62384", "obsDt": "2025-12-23 08:38", "howMany": 1, "lat": 40.257667, "lng": -87.623838, "obsValid": true, "obsReviewed": false, "locationPrivate": true, "subId": "S289858030"}, {"speciesCode": "normoc", "comName": "Northern Mockingbird", "sciName": "Mimus polyglottos", "locId": "L45603025", "locName": "16979 E County Road 2705 N, Danville US-IL 40.25767, -87.62384", "obsDt": "2025-12-23 08:38", "howMany": 1, "lat": 40.257667, "lng": -87.623838, "obsValid": true, "obsReviewed": false, "locationPrivate": true, "subId": "S289858030"}, {"speciesCode": "easblu", "comName": "Eastern Bluebird", "sciName": "Sialia sialis", "locId": "L45603025", "locName": "16979 E County Road 2705 N, Danville US-IL 40.25767, -87.62384", "obsDt": "2025-12-23 08:38", "howMany": 2, "lat": 40.257667, "lng": -87.623838, "obsValid": true, "obsReviewed": false, "locationPrivate": true, "subId": "S289858030"}, {"speciesCode": "herthr", "comName": "Hermit Thrush", "sciName": "Catharus guttatus", "locId": "L45603025", "locName": "16979 E County Road 2705 N, Danville US-IL 40.25767, -87.62384", "obsDt": "2025-12-23 08:38", "howMany": 1, "lat": 40.257667, "lng": -87.623838, "obsValid": true, "obsReviewed": false, "locationPrivate": true, "subId": "S289858030"}, {"speciesCode": "amerob", "comName": "American Robin", "sciName": "Turdus migratorius", "locId": "L45603025", "locName": "16979 E County Road 2705 N, Danville US-IL 40.25767, -87.62384", "obsDt": "2025-12-23 08:38", "howMany": 5, "lat": 40.257667, "lng": -87.623838, "obsValid": true, "obsReviewed": false, "locationPrivate": true, "subId": "S289858030"}, {"speciesCode": "houspa", "comName": "House Sparrow", "sciName": "Passer domesticus", "locId": "L45603025", "locName": "16979 E County Road 2705 N, Danville US-IL 40.25767, -87.62384", "obsDt": "2025-12-23 08:38", "howMany": 2, "lat": 40.257667, "lng": -87.623838, "obsValid": true, "obsReviewed": false, "locationPrivate": true, "subId": "S289858030", "exoticCategory": "N"}, {"speciesCode": "houfin", "comName": "House Finch", "sciName": "Haemorhous mexicanus", "locId": "L45603025", "locName": "16979 E County Road 2705 N, Danville US-IL 40.25767, -87.62384", "obsDt": "2025-12-23 08:38", "howMany": 8, "lat": 40.257667, "lng": -87.623838, "obsValid": true, "obsReviewed": false, "locationPrivate": true, "subId": "S289858030", "exoticCategory": "N"}, {"speciesCode": "purfin", "comName": "Purple Finch", "sciName": "Haemorhous purpureus", "locId": "L45603025", "locName": "16979 E County Road 2705 N, Danville US-IL 40.25767, -87.62384", "obsDt": "2025-12-23 08:38", "howMany": 3, "lat": 40.257667, "lng": -87.623838, "obsValid": true, "obsReviewed": false, "locationPrivate": true, "subId": "S289858030"}, {"speciesCode": "pinsis", "comName": "Pine Siskin", "sciName": "Spinus pinus", "locId": "L45603025", "locName": "16979 E County Road 2705 N, Danville US-IL 40.25767, -87.62384", "obsDt": "2025-12-23 08:38", "howMany": 1, "lat": 40.257667, "lng": -87.623838, "obsValid": true, "obsReviewed": false, "locationPrivate": true, "subId": "S289858030"}, {"speciesCode": "amegfi", "comName": "American Goldfinch", "sciName": "Spinus tristis", "locId": "L45603025", "locName": "16979 E County Road 2705 N, Danville US-IL 40.25767, -87.62384", "obsDt": "2025-12-23 08:38", "howMany": 24, "lat": 40.257667, "lng": -87.623838, "obsValid": true, "obsReviewed": false, "locationPrivate": true, "subId": "S289858030"}, {"speciesCode": "amtspa", "comName": "American Tree Sparrow", "sciName": "Spizelloides arborea", "locId": "L45603025", "locName": "16979 E County Road 2705 N, Danville US-IL 40.25767, -87.62384", "obsDt": "2025-12-23 08:38", "howMany": 2, "lat": 40.257667, "lng": -87.623838, "obsValid": true, "obsReviewed": false, "locationPrivate": true, "subId": "S289858030"}, {"speciesCode": "foxspa", "comName": "Fox Sparrow", "sciName": "Passerella iliaca", "locId": "L45603025", "locName": "16979 E County Road 2705 N, Danville US-IL 40.25767, -87.62384", "obsDt": "2025-12-23 08:38", "howMany": 1, "lat": 40.257667, "lng": -87.623838, "obsValid": true, "obsReviewed": false, "locationPrivate": true, "subId": "S289858030"}, {"speciesCode": "daejun", "comName": "Dark-eyed Junco", "sciName": "Junco hyemalis", "locId": "L45603025", "locName": "16979 E County Road 2705 N, Danville US-IL 40.25767, -87.62384", "obsDt": "2025-12-23 08:38", "howMany": 14, "lat": 40.257667, "lng": -87.623838, "obsValid": true, "obsReviewed": false, "locationPrivate": true, "subId": "S289858030"}, {"speciesCode": "whcspa", "comName": "White-crowned Sparrow", "sciName": "Zonotrichia leucophrys", "locId": "L45603025", "locName": "16979 E County Road 2705 N, Danville US-IL 40.25767, -87.62384", "obsDt": "2025-12-23 08:38", "howMany": 1, "lat": 40.257667, "lng": -87.623838, "obsValid": true, "obsReviewed": false, "locationPrivate": true, "subId": "S289858030"}, {"speciesCode": "whtspa", "comName": "White-throated Sparrow", "sciName": "Zonotrichia albicollis", "locId": "L45603025", "locName": "16979 E County Road 2705 N, Danville US-IL 40.25767, -87.62384", "obsDt": "2025-12-23 08:38", "howMany": 3, "lat": 40.257667, "lng": -87.623838, "obsValid": true, "obsReviewed": false, "locationPrivate": true, "subId": "S289858030"}, {"speciesCode": "sonspa", "comName": "Song Sparrow", "sciName": "Melospiza melodia", "locId": "L45603025", "locName": "16979 E County Road 2705 N, Danville US-IL 40.25767, -87.62384", "obsDt": "2025-12-23 08:38", "howMany": 2, "lat": 40.257667, "lng": -87.623838, "obsValid": true, "obsReviewed": false, "locationPrivate": true, "subId": "S289858030"}, {"speciesCode": "bnhcow", "comName": "Brown-headed Cowbird", "sciName": "Molothrus ater", "locId": "L45603025", "locName": "16979 E County Road 2705 N, Danville US-IL 40.25767, -87.62384", "obsDt": "2025-12-23 08:38", "howMany": 2, "lat": 40.257667, "lng": -87.623838, "obsValid": true, "obsReviewed": false, "locationPrivate": true, "subId": "S289858030"}, {"speciesCode": "comgra", "comName": "Common Grackle", "sciName": "Quiscalus quiscula", "locId": "L45603025", "locName": "16979 E County Road 2705 N, Danville US-IL 40.25767, -87.62384", "obsDt": "2025-12-23 08:38", "howMany": 22, "lat": 40.257667, "lng": -87.623838, "obsValid": true, "obsReviewed": false, "locationPrivate": true, "subId": "S289858030"}, {"speciesCode": "yerwar", "comName": "Yellow-rumped Warbler", "sciName": "Setophaga coronata", "locId": "L45603025", "locName": "16979 E County Road 2705 N, Danville US-IL 40.25767, -87.62384", "obsDt": "2025-12-23 08:38", "howMany": 1, "lat": 40.257667, "lng": -87.623838, "obsValid": true, "obsReviewed": false, "locationPrivate": true, "subId": "S289858030"}, {"speciesCode": "norcar", "comName": "Northern Cardinal", "sciName": "Cardinalis cardinalis", "locId": "L45603025", "locName": "16979 E County Road 2705 N, Danville US-IL 40.25767, -87.62384", "obsDt": "2025-12-23 08:38", "howMany": 8, "lat": 40.257667, "lng": -87.623838, "obsValid": true, "obsReviewed": false, "locationPrivate": true, "subId": "S289858030"}, {"speciesCode": "gwfgoo", "comName": "Greater White-fronted Goose", "sciName": "Anser albifrons", "locId": "L17808607", "locName": "Suncrest Drive, Danville", "obsDt": "2025-12-23 07:30", "howMany": 3, "lat": 40.1777763, "lng": -87.6354141, "obsValid": true, "obsReviewed": false, "locationPrivate": true, "subId": "S289908364"}, {"speciesCode": "rehwoo", "comName": "Red-headed Woodpecker", "sciName": "Melanerpes erythrocephalus", "locId": "L17808607", "locName": "Suncrest Drive, Danville", "obsDt": "2025-12-23 07:30", "howMany": 2, "lat": 40.1777763, "lng": -87.6354141, "obsValid": true, "obsReviewed": false, "locationPrivate": true, "subId": "S289908364"}, {"speciesCode": "eastow", "comName": "Eastern Towhee", "sciName": "Pipilo erythrophthalmus", "locId": "L17808607", "locName": "Suncrest Drive, Danville", "obsDt": "2025-12-23 07:30", "howMany": 1, "lat": 40.1777763, "lng": -87.6354141, "obsValid": true, "obsReviewed": false, "locationPrivate": true, "subId": "S289908364"}, {"speciesCode": "easmea", "comName": "Eastern Meadowlark", "sciName": "Sturnella magna", "locId": "L17808607", "locName": "Suncrest Drive, Danville", "obsDt": "2025-12-23 07:30", "howMany": 1, "lat": 40.1777763, "lng": -87.6354141, "obsValid": true, "obsReviewed": false, "locationPrivate": true, "subId": "S289908364"}, {"speciesCode": "rewbla", "comName": "Red-winged Blackbird", "sciName": "Agelaius phoeniceus", "locId": "L17808607", "locName": "Suncrest Drive, Danville", "obsDt": "2025-12-23 07:30", "howMany": 2, "lat": 40.1777763, "lng": -87.6354141, "obsValid": true, "obsReviewed": false, "locationPrivate": true, "subId": "S289908364"}]