[{"speciesCode": "cacgoo1", "comName": "Cackling Goose", "sciName": "Branta hutchinsii", "locId": "L56524800", "locName": "2100th St hayfield, Atlanta", "obsDt": "2025-12-22 08:44", "howMany": 2, "lat": 40.2232425, "lng": -89.2044786, "obsValid": true, "obsReviewed": false, "locationPrivate": true, "subId": "S291018664"}, {"speciesCode": "cangoo", "comName": "Canada Goose", "sciName": "Branta canadensis", "locId": "L56524800", "locName": "2100th St hayfield, Atlanta", "obsDt": "2025-12-22 08:44", "howMany": 750, "lat": 40.2232425, "lng": -89.2044786, "obsValid": true, "obsReviewed": false, "locationPrivate": true, "subId": "S291018664"}, {"speciesCode": "moudov", "comName": "Mourning Dove", "sciName": "Zenaida macroura", "locId": "L56524800", "locName": "2100th St hayfield, Atlanta", "obsDt": "2025-12-22 08:44", "howMany": 125, "lat": 40.2232425, "lng": -89.2044786, "obsValid": true, "obsReviewed": false, "locationPrivate": true, "subId": "S291018664"}, {"speciesCode": "logshr", "comName": "Loggerhead Shrike", "sciName": "Lanius ludovicianus", "locId": "L56524800", "locName": "2100th St hayfield, Atlanta", "obsDt": "2025-12-22 08:44", "howMany": 1, "lat": 40.2232425, "lng": -89.2044786, "obsValid": true, "obsReviewed": true, "locationPrivate": true, "subId": "S291018664"}]