[{"speciesCode": "snogoo", "comName": "Snow Goose", "sciName": "Anser caerulescens", "locId": "L17264472", "locName": "Private property", "obsDt": "2025-12-24 23:13", "lat": 39.505304, "lng": -88.086179, "obsValid": true, "obsReviewed": false, "locationPrivate": true, "subId": "S290084634"}, {"speciesCode": "gwfgoo", "comName": "Greater White-fronted Goose", "sciName": "Anser albifrons", "locId": "L17264472", "locName": "Private property", "obsDt": "2025-12-24 23:13", "lat": 39.505304, "lng": -88.086179, "obsValid": true, "obsReviewed": false, "locationPrivate": true, "subId": "S290084634"}, {"speciesCode": "cangoo", "comName": "Canada Goose", "sciName": "Branta canadensis", "locId": "L28687314", "locName": "The Magic Stump", "obsDt": "2025-12-24 15:50", "howMany": 5, "lat": 39.63053, "lng": -88.2418665, "obsValid": true, "obsReviewed": false, "locationPrivate": false, "subId": "S290059338"}, {"speciesCode": "rocpig", "comName": "Rock Pigeon", "sciName": "Columba livia", "locId": "L28687314", "locName": "The Magic Stump", "obsDt": "2025-12-24 15:50", "howMany": 4, "lat": 39.63053, "lng": -88.2418665, "obsValid": true, "obsReviewed": false, "locationPrivate": false, "subId": "S290059338", "exoticCategory": "N"}, {"speciesCode": "norhar2", "comName": "Northern Harrier", "sciName": "Circus hudsonius", "locId": "L28687314", "locName": "The Magic Stump", "obsDt": "2025-12-24 15:50", "howMany": 2, "lat": 39.63053, "lng": -88.2418665, "obsValid": true, "obsReviewed": false, "locationPrivate": false, "subId": "S290059338"}, {"speciesCode": "merlin", "comName": "Merlin", "sciName": "Falco columbarius", "locId": "L28687314", "locName": "The Magic Stump", "obsDt": "2025-12-24 15:50", "howMany": 1, "lat": 39.63053, "lng": -88.2418665, "obsValid": true, "obsReviewed": false, "locationPrivate": false, "subId": "S290059338"}, {"speciesCode": "amecro", "comName": "American Crow", "sciName": "Corvus brachyrhynchos", "locId": "L28687314", "locName": "The Magic Stump", "obsDt": "2025-12-24 15:50", "howMany": 40, "lat": 39.63053, "lng": -88.2418665, "obsValid": true, "obsReviewed": false, "locationPrivate": false, "subId": "S290059338"}, {"speciesCode": "eursta", "comName": "European Starling", "sciName": "Sturnus vulgaris", "locId": "L28687314", "locName": "The Magic Stump", "obsDt": "2025-12-24 15:50", "howMany": 38, "lat": 39.63053, "lng": -88.2418665, "obsValid": true, "obsReviewed": false, "locationPrivate": false, "subId": "S290059338", "exoticCategory": "N"}, {"speciesCode": "moudov", "comName": "Mourning Dove", "sciName": "Zenaida macroura", "locId": "L5003734", "locName": "US-Illinois-Charleston-1400E - 39.615x-88.214 - Oct 21, 2016 3:03 PM", "obsDt": "2025-12-24 12:48", "howMany": 1, "lat": 39.614573, "lng": -88.2140911, "obsValid": true, "obsReviewed": false, "locationPrivate": true, "subId": "S290046134"}, {"speciesCode": "rethaw", "comName": "Red-tailed Hawk", "sciName": "Buteo jamaicensis", "locId": "L5003734", "locName": "US-Illinois-Charleston-1400E - 39.615x-88.214 - Oct 21, 2016 3:03 PM", "obsDt": "2025-12-24 12:48", "howMany": 1, "lat": 39.614573, "lng": -88.2140911, "obsValid": true, "obsReviewed": false, "locationPrivate": true, "subId": "S290046134"}, {"speciesCode": "snoowl1", "comName": "Snowy Owl", "sciName": "Bubo scandiacus", "locId": "L5003734", "locName": "US-Illinois-Charleston-1400E - 39.615x-88.214 - Oct 21, 2016 3:03 PM", "obsDt": "2025-12-24 12:48", "howMany": 1, "lat": 39.614573, "lng": -88.2140911, "obsValid": true, "obsReviewed": true, "locationPrivate": true, "subId": "S290046134"}, {"speciesCode": "amekes", "comName": "American Kestrel", "sciName": "Falco sparverius", "locId": "L5003734", "locName": "US-Illinois-Charleston-1400E - 39.615x-88.214 - Oct 21, 2016 3:03 PM", "obsDt": "2025-12-24 12:48", "howMany": 2, "lat": 39.614573, "lng": -88.2140911, "obsValid": true, "obsReviewed": false, "locationPrivate": true, "subId": "S290046134"}, {"speciesCode": "horlar", "comName": "Horned Lark", "sciName": "Eremophila alpestris", "locId": "L5003734", "locName": "US-Illinois-Charleston-1400E - 39.615x-88.214 - Oct 21, 2016 3:03 PM", "obsDt": "2025-12-24 12:48", "howMany": 4, "lat": 39.614573, "lng": -88.2140911, "obsValid": true, "obsReviewed": false, "locationPrivate": true, "subId": "S290046134"}, {"speciesCode": "rebwoo", "comName": "Red-bellied Woodpecker", "sciName": "Melanerpes carolinus", "locId": "L17264472", "locName": "Private property", "obsDt": "2025-12-24 11:11", "howMany": 1, "lat": 39.505304, "lng": -88.086179, "obsValid": true, "obsReviewed": false, "locationPrivate": true, "subId": "S290045299"}, {"speciesCode": "dowwoo", "comName": "Downy Woodpecker", "sciName": "Dryobates pubescens", "locId": "L17264472", "locName": "Private property", "obsDt": "2025-12-24 11:11", "howMany": 3, "lat": 39.505304, "lng": -88.086179, "obsValid": true, "obsReviewed": false, "locationPrivate": true, "subId": "S290045299"}, {"speciesCode": "haiwoo", "comName": "Hairy Woodpecker", "sciName": "Leuconotopicus villosus", "locId": "L17264472", "locName": "Private property", "obsDt": "2025-12-24 11:11", "howMany": 1, "lat": 39.505304, "lng": -88.086179, "obsValid": true, "obsReviewed": false, "locationPrivate": true, "subId": "S290045299"}, {"speciesCode": "pilwoo", "comName": "Pileated Woodpecker", "sciName": "Dryocopus pileatus", "locId": "L17264472", "locName": "Private property", "obsDt": "2025-12-24 11:11", "howMany": 1, "lat": 39.505304, "lng": -88.086179, "obsValid": true, "obsReviewed": false, "locationPrivate": true, "subId": "S290045299"}, {"speciesCode": "blujay", "comName": "Blue Jay", "sciName": "Cyanocitta cristata", "locId": "L17264472", "locName": "Private property", "obsDt": "2025-12-24 11:11", "howMany": 1, "lat": 39.505304, "lng": -88.086179, "obsValid": true, "obsReviewed": false, "locationPrivate": true, "subId": "S290045299"}, {"speciesCode": "carchi", "comName": "Carolina Chickadee", "sciName": "Poecile carolinensis", "locId": "L17264472", "locName": "Private property", "obsDt": "2025-12-24 11:11", "howMany": 2, "lat": 39.505304, "lng": -88.086179, "obsValid": true, "obsReviewed": false, "locationPrivate": true, "subId": "S290045299"}, {"speciesCode": "tuftit", "comName": "Tufted Titmouse", "sciName": "Baeolophus bicolor", "locId": "L17264472", "locName": "Private property", "obsDt": "2025-12-24 11:11", "howMany": 5, "lat": 39.505304, "lng": -88.086179, "obsValid": true, "obsReviewed": false, "locationPrivate": true, "subId": "S290045299"}, {"speciesCode": "whbnut", "comName": "White-breasted Nuthatch", "sciName": "Sitta carolinensis", "locId": "L17264472", "locName": "Private property", "obsDt": "2025-12-24 11:11", "howMany": 2, "lat": 39.505304, "lng": -88.086179, "obsValid": true, "obsReviewed": false, "locationPrivate": true, "subId": "S290045299"}, {"speciesCode": "rebnut", "comName": "Red-breasted Nuthatch", "sciName": "Sitta canadensis", "locId": "L17264472", "locName": "Private property", "obsDt": "2025-12-24 11:11", "howMany": 3, "lat": 39.505304, "lng": -88.086179, "obsValid": true, "obsReviewed": false, "locationPrivate": true, "subId": "S290045299"}, {"speciesCode": "carwre", "comName": "Carolina Wren", "sciName": "Thryothorus ludovicianus", "locId": "L17264472", "locName": "Private property", "obsDt": "2025-12-24 11:11", "howMany": 1, "lat": 39.505304, "lng": -88.086179, "obsValid": true, "obsReviewed": false, "locationPrivate": true, "subId": "S290045299"}, {"speciesCode": "houspa", "comName": "House Sparrow", "sciName": "Passer domesticus", "locId": "L17264472", "locName": "Private property", "obsDt": "2025-12-24 11:11", "howMany": 2, "lat": 39.505304, "lng": -88.086179, "obsValid": true, "obsReviewed": false, "locationPrivate": true, "subId": "S290045299", "exoticCategory": "N"}, {"speciesCode": "houfin", "comName": "House Finch", "sciName": "Haemorhous mexicanus", "locId": "L17264472", "locName": "Private property", "obsDt": "2025-12-24 11:11", "howMany": 6, "lat": 39.505304, "lng": -88.086179, "obsValid": true, "obsReviewed": false, "locationPrivate": true, "subId": "S290045299", "exoticCategory": "N"}, {"speciesCode": "purfin", "comName": "Purple Finch", "sciName": "Haemorhous purpureus", "locId": "L17264472", "locName": "Private property", "obsDt": "2025-12-24 11:11", "howMany": 1, "lat": 39.505304, "lng": -88.086179, "obsValid": true, "obsReviewed": false, "locationPrivate": true, "subId": "S290045299"}, {"speciesCode": "amegfi", "comName": "American Goldfinch", "sciName": "Spinus tristis", "locId": "L17264472", "locName": "Private property", "obsDt": "2025-12-24 11:11", "howMany": 5, "lat": 39.505304, "lng": -88.086179, "obsValid": true, "obsReviewed": false, "locationPrivate": true, "subId": "S290045299"}, {"speciesCode": "daejun", "comName": "Dark-eyed Junco", "sciName": "Junco hyemalis", "locId": "L17264472", "locName": "Private property", "obsDt": "2025-12-24 11:11", "howMany": 4, "lat": 39.505304, "lng": -88.086179, "obsValid": true, "obsReviewed": false, "locationPrivate": true, "subId": "S290045299"}, {"speciesCode": "whtspa", "comName": "White-throated Sparrow", "sciName": "Zonotrichia albicollis", "locId": "L17264472", "locName": "Private property", "obsDt": "2025-12-24 11:11", "howMany": 2, "lat": 39.505304, "lng": -88.086179, "obsValid": true, "obsReviewed": false, "locationPrivate": true, "subId": "S290045299"}, {"speciesCode": "norcar", "comName": "Northern Cardinal", "sciName": "Cardinalis cardinalis", "locId": "L17264472", "locName": "Private property", "obsDt": "2025-12-24 11:11", "howMany": 3, "lat": 39.505304, "lng": -88.086179, "obsValid": true, "obsReviewed": false, "locationPrivate": true, "subId": "S290045299"}]