[{"speciesCode": "horlar", "comName": "Horned Lark", "sciName": "Eremophila alpestris", "locId": "L55971991", "locName": "16100\u201316164 Township Road 1300 E, Bradford US-IL 41.21176, -89.73470", "obsDt": "2025-12-14 09:28", "howMany": 6, "lat": 41.211764, "lng": -89.734698, "obsValid": true, "obsReviewed": false, "locationPrivate": true, "subId": "S288563005"}, {"speciesCode": "laplon", "comName": "Lapland Longspur", "sciName": "Calcarius lapponicus", "locId": "L55971991", "locName": "16100\u201316164 Township Road 1300 E, Bradford US-IL 41.21176, -89.73470", "obsDt": "2025-12-14 09:28", "howMany": 2, "lat": 41.211764, "lng": -89.734698, "obsValid": true, "obsReviewed": false, "locationPrivate": true, "subId": "S288563005"}, {"speciesCode": "snobun", "comName": "Snow Bunting", "sciName": "Plectrophenax nivalis", "locId": "L55971991", "locName": "16100\u201316164 Township Road 1300 E, Bradford US-IL 41.21176, -89.73470", "obsDt": "2025-12-14 09:28", "howMany": 2, "lat": 41.211764, "lng": -89.734698, "obsValid": true, "obsReviewed": false, "locationPrivate": true, "subId": "S288563005"}, {"speciesCode": "rethaw", "comName": "Red-tailed Hawk", "sciName": "Buteo jamaicensis", "locId": "L55971508", "locName": "10616\u201310698 E Osceola Rd, Bradford US-IL 41.21351, -89.77557", "obsDt": "2025-12-14 07:00", "howMany": 5, "lat": 41.213505, "lng": -89.775573, "obsValid": true, "obsReviewed": false, "locationPrivate": true, "subId": "S288560818"}, {"speciesCode": "norfli", "comName": "Northern Flicker", "sciName": "Colaptes auratus", "locId": "L55971508", "locName": "10616\u201310698 E Osceola Rd, Bradford US-IL 41.21351, -89.77557", "obsDt": "2025-12-14 07:00", "howMany": 2, "lat": 41.213505, "lng": -89.775573, "obsValid": true, "obsReviewed": false, "locationPrivate": true, "subId": "S288560818"}, {"speciesCode": "blujay", "comName": "Blue Jay", "sciName": "Cyanocitta cristata", "locId": "L55971508", "locName": "10616\u201310698 E Osceola Rd, Bradford US-IL 41.21351, -89.77557", "obsDt": "2025-12-14 07:00", "howMany": 1, "lat": 41.213505, "lng": -89.775573, "obsValid": true, "obsReviewed": false, "locationPrivate": true, "subId": "S288560818"}, {"speciesCode": "amecro", "comName": "American Crow", "sciName": "Corvus brachyrhynchos", "locId": "L55971508", "locName": "10616\u201310698 E Osceola Rd, Bradford US-IL 41.21351, -89.77557", "obsDt": "2025-12-14 07:00", "howMany": 2, "lat": 41.213505, "lng": -89.775573, "obsValid": true, "obsReviewed": false, "locationPrivate": true, "subId": "S288560818"}, {"speciesCode": "eutspa", "comName": "Eurasian Tree Sparrow", "sciName": "Passer montanus", "locId": "L55971508", "locName": "10616\u201310698 E Osceola Rd, Bradford US-IL 41.21351, -89.77557", "obsDt": "2025-12-14 07:00", "howMany": 3, "lat": 41.213505, "lng": -89.775573, "obsValid": true, "obsReviewed": false, "locationPrivate": true, "subId": "S288560818", "exoticCategory": "N"}, {"speciesCode": "amtspa", "comName": "American Tree Sparrow", "sciName": "Spizelloides arborea", "locId": "L55971508", "locName": "10616\u201310698 E Osceola Rd, Bradford US-IL 41.21351, -89.77557", "obsDt": "2025-12-14 07:00", "howMany": 15, "lat": 41.213505, "lng": -89.775573, "obsValid": true, "obsReviewed": false, "locationPrivate": true, "subId": "S288560818"}, {"speciesCode": "daejun", "comName": "Dark-eyed Junco", "sciName": "Junco hyemalis", "locId": "L55971508", "locName": "10616\u201310698 E Osceola Rd, Bradford US-IL 41.21351, -89.77557", "obsDt": "2025-12-14 07:00", "howMany": 15, "lat": 41.213505, "lng": -89.775573, "obsValid": true, "obsReviewed": false, "locationPrivate": true, "subId": "S288560818"}, {"speciesCode": "sonspa", "comName": "Song Sparrow", "sciName": "Melospiza melodia", "locId": "L55971508", "locName": "10616\u201310698 E Osceola Rd, Bradford US-IL 41.21351, -89.77557", "obsDt": "2025-12-14 07:00", "howMany": 1, "lat": 41.213505, "lng": -89.775573, "obsValid": true, "obsReviewed": false, "locationPrivate": true, "subId": "S288560818"}, {"speciesCode": "norcar", "comName": "Northern Cardinal", "sciName": "Cardinalis cardinalis", "locId": "L55971508", "locName": "10616\u201310698 E Osceola Rd, Bradford US-IL 41.21351, -89.77557", "obsDt": "2025-12-14 07:00", "howMany": 2, "lat": 41.213505, "lng": -89.775573, "obsValid": true, "obsReviewed": false, "locationPrivate": true, "subId": "S288560818"}]