[{"speciesCode": "dowwoo", "comName": "Downy Woodpecker", "sciName": "Dryobates pubescens", "locId": "L56258020", "locName": "23480 Dogwood Dr, Elsah US-IL 38.96855, -90.35896", "obsDt": "2025-12-23 14:22", "howMany": 1, "lat": 38.968551, "lng": -90.358959, "obsValid": true, "obsReviewed": false, "locationPrivate": true, "subId": "S289887347"}, {"speciesCode": "blujay", "comName": "Blue Jay", "sciName": "Cyanocitta cristata", "locId": "L56258020", "locName": "23480 Dogwood Dr, Elsah US-IL 38.96855, -90.35896", "obsDt": "2025-12-23 14:22", "howMany": 2, "lat": 38.968551, "lng": -90.358959, "obsValid": true, "obsReviewed": false, "locationPrivate": true, "subId": "S289887347"}, {"speciesCode": "amecro", "comName": "American Crow", "sciName": "Corvus brachyrhynchos", "locId": "L56258020", "locName": "23480 Dogwood Dr, Elsah US-IL 38.96855, -90.35896", "obsDt": "2025-12-23 14:22", "howMany": 2, "lat": 38.968551, "lng": -90.358959, "obsValid": true, "obsReviewed": false, "locationPrivate": true, "subId": "S289887347"}, {"speciesCode": "bkcchi", "comName": "Black-capped Chickadee", "sciName": "Poecile atricapillus", "locId": "L56258020", "locName": "23480 Dogwood Dr, Elsah US-IL 38.96855, -90.35896", "obsDt": "2025-12-23 14:22", "howMany": 1, "lat": 38.968551, "lng": -90.358959, "obsValid": true, "obsReviewed": false, "locationPrivate": true, "subId": "S289887347"}, {"speciesCode": "daejun", "comName": "Dark-eyed Junco", "sciName": "Junco hyemalis", "locId": "L56258020", "locName": "23480 Dogwood Dr, Elsah US-IL 38.96855, -90.35896", "obsDt": "2025-12-23 14:22", "howMany": 1, "lat": 38.968551, "lng": -90.358959, "obsValid": true, "obsReviewed": false, "locationPrivate": true, "subId": "S289887347"}, {"speciesCode": "whtspa", "comName": "White-throated Sparrow", "sciName": "Zonotrichia albicollis", "locId": "L56258020", "locName": "23480 Dogwood Dr, Elsah US-IL 38.96855, -90.35896", "obsDt": "2025-12-23 14:22", "howMany": 2, "lat": 38.968551, "lng": -90.358959, "obsValid": true, "obsReviewed": false, "locationPrivate": true, "subId": "S289887347"}]