[{"speciesCode": "truswa", "comName": "Trumpeter Swan", "sciName": "Cygnus buccinator", "locId": "L56144061", "locName": "10557 Gumtown Road, Virginia, Illinois, US (40.036, -90.252)", "obsDt": "2025-12-20 12:12", "howMany": 97, "lat": 40.0358793, "lng": -90.2517744, "obsValid": true, "obsReviewed": false, "locationPrivate": true, "subId": "S289366934"}, {"speciesCode": "horlar", "comName": "Horned Lark", "sciName": "Eremophila alpestris", "locId": "L56144061", "locName": "10557 Gumtown Road, Virginia, Illinois, US (40.036, -90.252)", "obsDt": "2025-12-20 12:12", "howMany": 3, "lat": 40.0358793, "lng": -90.2517744, "obsValid": true, "obsReviewed": false, "locationPrivate": true, "subId": "S289366934"}, {"speciesCode": "norbob", "comName": "Northern Bobwhite", "sciName": "Colinus virginianus", "locId": "L5573894", "locName": "US-Illinois-Beardstown-West Hagener Road - 39.941x-90.461", "obsDt": "2025-12-20 11:34", "howMany": 15, "lat": 39.9409982, "lng": -90.4612605, "obsValid": true, "obsReviewed": false, "locationPrivate": true, "subId": "S289357036"}, {"speciesCode": "houfin", "comName": "House Finch", "sciName": "Haemorhous mexicanus", "locId": "L22054558", "locName": "Jim Edgar Panther Creek State FWA--Herrmann Pond area", "obsDt": "2025-12-20 10:47", "howMany": 4, "lat": 40.032312, "lng": -90.124782, "obsValid": true, "obsReviewed": false, "locationPrivate": false, "subId": "S289346579", "exoticCategory": "N"}, {"speciesCode": "rebwoo", "comName": "Red-bellied Woodpecker", "sciName": "Melanerpes carolinus", "locId": "L56138587", "locName": "Creek Road, Chandlerville, Illinois, US (39.998, -90.1)", "obsDt": "2025-12-20 10:34", "howMany": 1, "lat": 39.997501, "lng": -90.0998577, "obsValid": true, "obsReviewed": false, "locationPrivate": true, "subId": "S289343264"}, {"speciesCode": "easblu", "comName": "Eastern Bluebird", "sciName": "Sialia sialis", "locId": "L56138587", "locName": "Creek Road, Chandlerville, Illinois, US (39.998, -90.1)", "obsDt": "2025-12-20 10:34", "howMany": 2, "lat": 39.997501, "lng": -90.0998577, "obsValid": true, "obsReviewed": false, "locationPrivate": true, "subId": "S289343264"}, {"speciesCode": "amerob", "comName": "American Robin", "sciName": "Turdus migratorius", "locId": "L56138587", "locName": "Creek Road, Chandlerville, Illinois, US (39.998, -90.1)", "obsDt": "2025-12-20 10:34", "howMany": 1, "lat": 39.997501, "lng": -90.0998577, "obsValid": true, "obsReviewed": false, "locationPrivate": true, "subId": "S289343264"}, {"speciesCode": "amtspa", "comName": "American Tree Sparrow", "sciName": "Spizelloides arborea", "locId": "L56138587", "locName": "Creek Road, Chandlerville, Illinois, US (39.998, -90.1)", "obsDt": "2025-12-20 10:34", "howMany": 25, "lat": 39.997501, "lng": -90.0998577, "obsValid": true, "obsReviewed": false, "locationPrivate": true, "subId": "S289343264"}, {"speciesCode": "daejun", "comName": "Dark-eyed Junco", "sciName": "Junco hyemalis", "locId": "L56138587", "locName": "Creek Road, Chandlerville, Illinois, US (39.998, -90.1)", "obsDt": "2025-12-20 10:34", "howMany": 15, "lat": 39.997501, "lng": -90.0998577, "obsValid": true, "obsReviewed": false, "locationPrivate": true, "subId": "S289343264"}, {"speciesCode": "whcspa", "comName": "White-crowned Sparrow", "sciName": "Zonotrichia leucophrys", "locId": "L56138587", "locName": "Creek Road, Chandlerville, Illinois, US (39.998, -90.1)", "obsDt": "2025-12-20 10:34", "howMany": 2, "lat": 39.997501, "lng": -90.0998577, "obsValid": true, "obsReviewed": false, "locationPrivate": true, "subId": "S289343264"}, {"speciesCode": "whtspa", "comName": "White-throated Sparrow", "sciName": "Zonotrichia albicollis", "locId": "L56138587", "locName": "Creek Road, Chandlerville, Illinois, US (39.998, -90.1)", "obsDt": "2025-12-20 10:34", "howMany": 3, "lat": 39.997501, "lng": -90.0998577, "obsValid": true, "obsReviewed": false, "locationPrivate": true, "subId": "S289343264"}, {"speciesCode": "cangoo", "comName": "Canada Goose", "sciName": "Branta canadensis", "locId": "L2355551", "locName": "Jim Edgar Panther Creek State Fish & Wildlife Area", "obsDt": "2025-12-20 10:13", "howMany": 80, "lat": 39.995547, "lng": -90.069083, "obsValid": true, "obsReviewed": false, "locationPrivate": false, "subId": "S289583828"}, {"speciesCode": "mallar3", "comName": "Mallard", "sciName": "Anas platyrhynchos", "locId": "L2355551", "locName": "Jim Edgar Panther Creek State Fish & Wildlife Area", "obsDt": "2025-12-20 10:13", "howMany": 3, "lat": 39.995547, "lng": -90.069083, "obsValid": true, "obsReviewed": false, "locationPrivate": false, "subId": "S289583828"}, {"speciesCode": "comgol", "comName": "Common Goldeneye", "sciName": "Bucephala clangula", "locId": "L2355551", "locName": "Jim Edgar Panther Creek State Fish & Wildlife Area", "obsDt": "2025-12-20 10:13", "howMany": 2, "lat": 39.995547, "lng": -90.069083, "obsValid": true, "obsReviewed": false, "locationPrivate": false, "subId": "S289583828"}, {"speciesCode": "rinphe1", "comName": "Ring-necked Pheasant", "sciName": "Phasianus colchicus", "locId": "L2355551", "locName": "Jim Edgar Panther Creek State Fish & Wildlife Area", "obsDt": "2025-12-20 10:13", "howMany": 2, "lat": 39.995547, "lng": -90.069083, "obsValid": true, "obsReviewed": false, "locationPrivate": false, "subId": "S289583828", "exoticCategory": "N"}, {"speciesCode": "rethaw", "comName": "Red-tailed Hawk", "sciName": "Buteo jamaicensis", "locId": "L2355551", "locName": "Jim Edgar Panther Creek State Fish & Wildlife Area", "obsDt": "2025-12-20 10:13", "howMany": 2, "lat": 39.995547, "lng": -90.069083, "obsValid": true, "obsReviewed": false, "locationPrivate": false, "subId": "S289583828"}, {"speciesCode": "dowwoo", "comName": "Downy Woodpecker", "sciName": "Dryobates pubescens", "locId": "L2355551", "locName": "Jim Edgar Panther Creek State Fish & Wildlife Area", "obsDt": "2025-12-20 10:13", "howMany": 1, "lat": 39.995547, "lng": -90.069083, "obsValid": true, "obsReviewed": false, "locationPrivate": false, "subId": "S289583828"}, {"speciesCode": "norfli", "comName": "Northern Flicker", "sciName": "Colaptes auratus", "locId": "L2355551", "locName": "Jim Edgar Panther Creek State Fish & Wildlife Area", "obsDt": "2025-12-20 10:13", "howMany": 2, "lat": 39.995547, "lng": -90.069083, "obsValid": true, "obsReviewed": false, "locationPrivate": false, "subId": "S289583828"}, {"speciesCode": "norshr4", "comName": "Northern Shrike", "sciName": "Lanius borealis", "locId": "L2355551", "locName": "Jim Edgar Panther Creek State Fish & Wildlife Area", "obsDt": "2025-12-20 10:13", "howMany": 1, "lat": 39.995547, "lng": -90.069083, "obsValid": true, "obsReviewed": true, "locationPrivate": false, "subId": "S289583828"}, {"speciesCode": "blujay", "comName": "Blue Jay", "sciName": "Cyanocitta cristata", "locId": "L2355551", "locName": "Jim Edgar Panther Creek State Fish & Wildlife Area", "obsDt": "2025-12-20 10:13", "howMany": 3, "lat": 39.995547, "lng": -90.069083, "obsValid": true, "obsReviewed": false, "locationPrivate": false, "subId": "S289583828"}, {"speciesCode": "amecro", "comName": "American Crow", "sciName": "Corvus brachyrhynchos", "locId": "L2355551", "locName": "Jim Edgar Panther Creek State Fish & Wildlife Area", "obsDt": "2025-12-20 10:13", "howMany": 2, "lat": 39.995547, "lng": -90.069083, "obsValid": true, "obsReviewed": false, "locationPrivate": false, "subId": "S289583828"}, {"speciesCode": "bkcchi", "comName": "Black-capped Chickadee", "sciName": "Poecile atricapillus", "locId": "L2355551", "locName": "Jim Edgar Panther Creek State Fish & Wildlife Area", "obsDt": "2025-12-20 10:13", "howMany": 1, "lat": 39.995547, "lng": -90.069083, "obsValid": true, "obsReviewed": false, "locationPrivate": false, "subId": "S289583828"}, {"speciesCode": "tuftit", "comName": "Tufted Titmouse", "sciName": "Baeolophus bicolor", "locId": "L2355551", "locName": "Jim Edgar Panther Creek State Fish & Wildlife Area", "obsDt": "2025-12-20 10:13", "howMany": 1, "lat": 39.995547, "lng": -90.069083, "obsValid": true, "obsReviewed": false, "locationPrivate": false, "subId": "S289583828"}, {"speciesCode": "whbnut", "comName": "White-breasted Nuthatch", "sciName": "Sitta carolinensis", "locId": "L2355551", "locName": "Jim Edgar Panther Creek State Fish & Wildlife Area", "obsDt": "2025-12-20 10:13", "howMany": 1, "lat": 39.995547, "lng": -90.069083, "obsValid": true, "obsReviewed": false, "locationPrivate": false, "subId": "S289583828"}, {"speciesCode": "amegfi", "comName": "American Goldfinch", "sciName": "Spinus tristis", "locId": "L2355551", "locName": "Jim Edgar Panther Creek State Fish & Wildlife Area", "obsDt": "2025-12-20 10:13", "howMany": 17, "lat": 39.995547, "lng": -90.069083, "obsValid": true, "obsReviewed": false, "locationPrivate": false, "subId": "S289583828"}, {"speciesCode": "swaspa", "comName": "Swamp Sparrow", "sciName": "Melospiza georgiana", "locId": "L2355551", "locName": "Jim Edgar Panther Creek State Fish & Wildlife Area", "obsDt": "2025-12-20 10:13", "howMany": 1, "lat": 39.995547, "lng": -90.069083, "obsValid": true, "obsReviewed": false, "locationPrivate": false, "subId": "S289583828"}, {"speciesCode": "norcar", "comName": "Northern Cardinal", "sciName": "Cardinalis cardinalis", "locId": "L2355551", "locName": "Jim Edgar Panther Creek State Fish & Wildlife Area", "obsDt": "2025-12-20 10:13", "howMany": 2, "lat": 39.995547, "lng": -90.069083, "obsValid": true, "obsReviewed": false, "locationPrivate": false, "subId": "S289583828"}, {"speciesCode": "baleag", "comName": "Bald Eagle", "sciName": "Haliaeetus leucocephalus", "locId": "L22055662", "locName": "Jim Edgar Panther Creek State FWA--Drake Lake Area", "obsDt": "2025-12-20 09:58", "howMany": 1, "lat": 40.0024264, "lng": -90.0857287, "obsValid": true, "obsReviewed": false, "locationPrivate": false, "subId": "S289336065"}, {"speciesCode": "amekes", "comName": "American Kestrel", "sciName": "Falco sparverius", "locId": "L5642663", "locName": "Jim Edgar Panther Creek State FWA--Westlake Day Use Area and Boat Access", "obsDt": "2025-12-20 09:17", "howMany": 3, "lat": 39.9957064, "lng": -90.0611812, "obsValid": true, "obsReviewed": false, "locationPrivate": false, "subId": "S289333640"}]