[{"speciesCode": "canvas", "comName": "Canvasback", "sciName": "Aythya valisineria", "locId": "L2326406", "locName": "Silver Lake Park", "obsDt": "2025-12-28 14:40", "howMany": 1, "lat": 38.7649857, "lng": -89.6931633, "obsValid": true, "obsReviewed": false, "locationPrivate": false, "subId": "S291002309"}, {"speciesCode": "lessca", "comName": "Lesser Scaup", "sciName": "Aythya affinis", "locId": "L2326406", "locName": "Silver Lake Park", "obsDt": "2025-12-28 14:40", "howMany": 2, "lat": 38.7649857, "lng": -89.6931633, "obsValid": true, "obsReviewed": false, "locationPrivate": false, "subId": "S291002309"}, {"speciesCode": "rudduc", "comName": "Ruddy Duck", "sciName": "Oxyura jamaicensis", "locId": "L2326406", "locName": "Silver Lake Park", "obsDt": "2025-12-28 14:40", "howMany": 1, "lat": 38.7649857, "lng": -89.6931633, "obsValid": true, "obsReviewed": false, "locationPrivate": false, "subId": "S291002309"}, {"speciesCode": "cangoo", "comName": "Canada Goose", "sciName": "Branta canadensis", "locId": "L283812", "locName": "Melvin Price Lock and Dam 26, Alton", "obsDt": "2025-12-28 13:51", "howMany": 13, "lat": 38.8711955, "lng": -90.1502198, "obsValid": true, "obsReviewed": false, "locationPrivate": false, "subId": "S292398201"}, {"speciesCode": "comgol", "comName": "Common Goldeneye", "sciName": "Bucephala clangula", "locId": "L283812", "locName": "Melvin Price Lock and Dam 26, Alton", "obsDt": "2025-12-28 13:51", "howMany": 15, "lat": 38.8711955, "lng": -90.1502198, "obsValid": true, "obsReviewed": false, "locationPrivate": false, "subId": "S292398201"}, {"speciesCode": "rocpig", "comName": "Rock Pigeon", "sciName": "Columba livia", "locId": "L283812", "locName": "Melvin Price Lock and Dam 26, Alton", "obsDt": "2025-12-28 13:51", "howMany": 150, "lat": 38.8711955, "lng": -90.1502198, "obsValid": true, "obsReviewed": false, "locationPrivate": false, "subId": "S292398201", "exoticCategory": "N"}, {"speciesCode": "ribgul", "comName": "Ring-billed Gull", "sciName": "Larus delawarensis", "locId": "L283812", "locName": "Melvin Price Lock and Dam 26, Alton", "obsDt": "2025-12-28 13:51", "howMany": 4, "lat": 38.8711955, "lng": -90.1502198, "obsValid": true, "obsReviewed": false, "locationPrivate": false, "subId": "S292398201"}, {"speciesCode": "baleag", "comName": "Bald Eagle", "sciName": "Haliaeetus leucocephalus", "locId": "L283812", "locName": "Melvin Price Lock and Dam 26, Alton", "obsDt": "2025-12-28 13:51", "howMany": 1, "lat": 38.8711955, "lng": -90.1502198, "obsValid": true, "obsReviewed": false, "locationPrivate": false, "subId": "S292398201"}, {"speciesCode": "carwre", "comName": "Carolina Wren", "sciName": "Thryothorus ludovicianus", "locId": "L283812", "locName": "Melvin Price Lock and Dam 26, Alton", "obsDt": "2025-12-28 13:51", "howMany": 1, "lat": 38.8711955, "lng": -90.1502198, "obsValid": true, "obsReviewed": false, "locationPrivate": false, "subId": "S292398201"}, {"speciesCode": "truswa", "comName": "Trumpeter Swan", "sciName": "Cygnus buccinator", "locId": "L56479295", "locName": "Horseshoe Lake State Park, Pontoon Beach US-IL 38.70743, -90.07332", "obsDt": "2025-12-28 13:15", "howMany": 1, "lat": 38.707431, "lng": -90.073321, "obsValid": true, "obsReviewed": false, "locationPrivate": true, "subId": "S291038349"}, {"speciesCode": "grbher3", "comName": "Great Blue Heron", "sciName": "Ardea herodias", "locId": "L23789961", "locName": "Watershed Nature Center", "obsDt": "2025-12-28 13:08", "howMany": 1, "lat": 38.816843, "lng": -89.979605, "obsValid": true, "obsReviewed": false, "locationPrivate": true, "subId": "S290846887"}, {"speciesCode": "turvul", "comName": "Turkey Vulture", "sciName": "Cathartes aura", "locId": "L23789961", "locName": "Watershed Nature Center", "obsDt": "2025-12-28 13:08", "howMany": 6, "lat": 38.816843, "lng": -89.979605, "obsValid": true, "obsReviewed": false, "locationPrivate": true, "subId": "S290846887"}, {"speciesCode": "carchi", "comName": "Carolina Chickadee", "sciName": "Poecile carolinensis", "locId": "L23789961", "locName": "Watershed Nature Center", "obsDt": "2025-12-28 13:08", "howMany": 1, "lat": 38.816843, "lng": -89.979605, "obsValid": true, "obsReviewed": true, "locationPrivate": true, "subId": "S290846887"}, {"speciesCode": "tuftit", "comName": "Tufted Titmouse", "sciName": "Baeolophus bicolor", "locId": "L23789961", "locName": "Watershed Nature Center", "obsDt": "2025-12-28 13:08", "howMany": 1, "lat": 38.816843, "lng": -89.979605, "obsValid": true, "obsReviewed": false, "locationPrivate": true, "subId": "S290846887"}, {"speciesCode": "houfin", "comName": "House Finch", "sciName": "Haemorhous mexicanus", "locId": "L23789961", "locName": "Watershed Nature Center", "obsDt": "2025-12-28 13:08", "howMany": 2, "lat": 38.816843, "lng": -89.979605, "obsValid": true, "obsReviewed": false, "locationPrivate": true, "subId": "S290846887", "exoticCategory": "N"}, {"speciesCode": "rewbla", "comName": "Red-winged Blackbird", "sciName": "Agelaius phoeniceus", "locId": "L23789961", "locName": "Watershed Nature Center", "obsDt": "2025-12-28 13:08", "howMany": 7, "lat": 38.816843, "lng": -89.979605, "obsValid": true, "obsReviewed": false, "locationPrivate": true, "subId": "S290846887"}, {"speciesCode": "gadwal", "comName": "Gadwall", "sciName": "Mareca strepera", "locId": "L56479295", "locName": "Horseshoe Lake State Park, Pontoon Beach US-IL 38.70743, -90.07332", "obsDt": "2025-12-28 12:35", "howMany": 4, "lat": 38.707431, "lng": -90.073321, "obsValid": true, "obsReviewed": false, "locationPrivate": true, "subId": "S290835656"}, {"speciesCode": "mallar3", "comName": "Mallard", "sciName": "Anas platyrhynchos", "locId": "L56479295", "locName": "Horseshoe Lake State Park, Pontoon Beach US-IL 38.70743, -90.07332", "obsDt": "2025-12-28 12:35", "howMany": 20, "lat": 38.707431, "lng": -90.073321, "obsValid": true, "obsReviewed": false, "locationPrivate": true, "subId": "S290835656"}, {"speciesCode": "dowwoo", "comName": "Downy Woodpecker", "sciName": "Dryobates pubescens", "locId": "L11901646", "locName": "Willoughby Heritage Farm", "obsDt": "2025-12-28 11:39", "howMany": 1, "lat": 38.6753774, "lng": -90.0014337, "obsValid": true, "obsReviewed": false, "locationPrivate": false, "subId": "S290821712"}, {"speciesCode": "blujay", "comName": "Blue Jay", "sciName": "Cyanocitta cristata", "locId": "L11901646", "locName": "Willoughby Heritage Farm", "obsDt": "2025-12-28 11:39", "howMany": 1, "lat": 38.6753774, "lng": -90.0014337, "obsValid": true, "obsReviewed": false, "locationPrivate": false, "subId": "S290821712"}, {"speciesCode": "amecro", "comName": "American Crow", "sciName": "Corvus brachyrhynchos", "locId": "L11901646", "locName": "Willoughby Heritage Farm", "obsDt": "2025-12-28 11:39", "howMany": 4, "lat": 38.6753774, "lng": -90.0014337, "obsValid": true, "obsReviewed": false, "locationPrivate": false, "subId": "S290821712"}, {"speciesCode": "easblu", "comName": "Eastern Bluebird", "sciName": "Sialia sialis", "locId": "L11901646", "locName": "Willoughby Heritage Farm", "obsDt": "2025-12-28 11:39", "howMany": 1, "lat": 38.6753774, "lng": -90.0014337, "obsValid": true, "obsReviewed": false, "locationPrivate": false, "subId": "S290821712"}, {"speciesCode": "daejun", "comName": "Dark-eyed Junco", "sciName": "Junco hyemalis", "locId": "L11901646", "locName": "Willoughby Heritage Farm", "obsDt": "2025-12-28 11:39", "howMany": 3, "lat": 38.6753774, "lng": -90.0014337, "obsValid": true, "obsReviewed": false, "locationPrivate": false, "subId": "S290821712"}, {"speciesCode": "eursta", "comName": "European Starling", "sciName": "Sturnus vulgaris", "locId": "L56341202", "locName": "Backyard", "obsDt": "2025-12-28 08:42", "howMany": 3, "lat": 38.691829, "lng": -89.953267, "obsValid": true, "obsReviewed": false, "locationPrivate": true, "subId": "S290769759", "exoticCategory": "N"}, {"speciesCode": "moudov", "comName": "Mourning Dove", "sciName": "Zenaida macroura", "locId": "L3755467", "locName": "Home", "obsDt": "2025-12-28 07:50", "howMany": 3, "lat": 38.8013371, "lng": -89.9613745, "obsValid": true, "obsReviewed": false, "locationPrivate": true, "subId": "S290922583"}, {"speciesCode": "rebwoo", "comName": "Red-bellied Woodpecker", "sciName": "Melanerpes carolinus", "locId": "L3755467", "locName": "Home", "obsDt": "2025-12-28 07:50", "howMany": 2, "lat": 38.8013371, "lng": -89.9613745, "obsValid": true, "obsReviewed": false, "locationPrivate": true, "subId": "S290922583"}, {"speciesCode": "whbnut", "comName": "White-breasted Nuthatch", "sciName": "Sitta carolinensis", "locId": "L3755467", "locName": "Home", "obsDt": "2025-12-28 07:50", "howMany": 1, "lat": 38.8013371, "lng": -89.9613745, "obsValid": true, "obsReviewed": false, "locationPrivate": true, "subId": "S290922583"}, {"speciesCode": "brncre", "comName": "Brown Creeper", "sciName": "Certhia americana", "locId": "L3755467", "locName": "Home", "obsDt": "2025-12-28 07:50", "howMany": 1, "lat": 38.8013371, "lng": -89.9613745, "obsValid": true, "obsReviewed": false, "locationPrivate": true, "subId": "S290922583"}, {"speciesCode": "normoc", "comName": "Northern Mockingbird", "sciName": "Mimus polyglottos", "locId": "L3755467", "locName": "Home", "obsDt": "2025-12-28 07:50", "howMany": 1, "lat": 38.8013371, "lng": -89.9613745, "obsValid": true, "obsReviewed": false, "locationPrivate": true, "subId": "S290922583"}, {"speciesCode": "amerob", "comName": "American Robin", "sciName": "Turdus migratorius", "locId": "L3755467", "locName": "Home", "obsDt": "2025-12-28 07:50", "howMany": 6, "lat": 38.8013371, "lng": -89.9613745, "obsValid": true, "obsReviewed": false, "locationPrivate": true, "subId": "S290922583"}, {"speciesCode": "houspa", "comName": "House Sparrow", "sciName": "Passer domesticus", "locId": "L3755467", "locName": "Home", "obsDt": "2025-12-28 07:50", "howMany": 3, "lat": 38.8013371, "lng": -89.9613745, "obsValid": true, "obsReviewed": false, "locationPrivate": true, "subId": "S290922583", "exoticCategory": "N"}, {"speciesCode": "pinsis", "comName": "Pine Siskin", "sciName": "Spinus pinus", "locId": "L3755467", "locName": "Home", "obsDt": "2025-12-28 07:50", "howMany": 1, "lat": 38.8013371, "lng": -89.9613745, "obsValid": true, "obsReviewed": false, "locationPrivate": true, "subId": "S290922583"}, {"speciesCode": "amegfi", "comName": "American Goldfinch", "sciName": "Spinus tristis", "locId": "L3755467", "locName": "Home", "obsDt": "2025-12-28 07:50", "howMany": 3, "lat": 38.8013371, "lng": -89.9613745, "obsValid": true, "obsReviewed": false, "locationPrivate": true, "subId": "S290922583"}, {"speciesCode": "whtspa", "comName": "White-throated Sparrow", "sciName": "Zonotrichia albicollis", "locId": "L3755467", "locName": "Home", "obsDt": "2025-12-28 07:50", "howMany": 6, "lat": 38.8013371, "lng": -89.9613745, "obsValid": true, "obsReviewed": false, "locationPrivate": true, "subId": "S290922583"}, {"speciesCode": "comgra", "comName": "Common Grackle", "sciName": "Quiscalus quiscula", "locId": "L3755467", "locName": "Home", "obsDt": "2025-12-28 07:50", "howMany": 37, "lat": 38.8013371, "lng": -89.9613745, "obsValid": true, "obsReviewed": false, "locationPrivate": true, "subId": "S290922583"}, {"speciesCode": "yerwar", "comName": "Yellow-rumped Warbler", "sciName": "Setophaga coronata", "locId": "L3755467", "locName": "Home", "obsDt": "2025-12-28 07:50", "howMany": 1, "lat": 38.8013371, "lng": -89.9613745, "obsValid": true, "obsReviewed": false, "locationPrivate": true, "subId": "S290922583"}, {"speciesCode": "norcar", "comName": "Northern Cardinal", "sciName": "Cardinalis cardinalis", "locId": "L3755467", "locName": "Home", "obsDt": "2025-12-28 07:50", "howMany": 8, "lat": 38.8013371, "lng": -89.9613745, "obsValid": true, "obsReviewed": false, "locationPrivate": true, "subId": "S290922583"}, {"speciesCode": "snogoo", "comName": "Snow Goose", "sciName": "Anser caerulescens", "locId": "L200627", "locName": "Horseshoe Lake State Park", "obsDt": "2025-12-28 07:40", "howMany": 35, "lat": 38.7039503, "lng": -90.0724398, "obsValid": true, "obsReviewed": false, "locationPrivate": false, "subId": "S290772995"}, {"speciesCode": "norsho", "comName": "Northern Shoveler", "sciName": "Spatula clypeata", "locId": "L200627", "locName": "Horseshoe Lake State Park", "obsDt": "2025-12-28 07:40", "howMany": 15, "lat": 38.7039503, "lng": -90.0724398, "obsValid": true, "obsReviewed": false, "locationPrivate": false, "subId": "S290772995"}, {"speciesCode": "norpin", "comName": "Northern Pintail", "sciName": "Anas acuta", "locId": "L200627", "locName": "Horseshoe Lake State Park", "obsDt": "2025-12-28 07:40", "howMany": 10, "lat": 38.7039503, "lng": -90.0724398, "obsValid": true, "obsReviewed": false, "locationPrivate": false, "subId": "S290772995"}, {"speciesCode": "hoomer", "comName": "Hooded Merganser", "sciName": "Lophodytes cucullatus", "locId": "L200627", "locName": "Horseshoe Lake State Park", "obsDt": "2025-12-28 07:40", "howMany": 1, "lat": 38.7039503, "lng": -90.0724398, "obsValid": true, "obsReviewed": false, "locationPrivate": false, "subId": "S290772995"}, {"speciesCode": "norhar2", "comName": "Northern Harrier", "sciName": "Circus hudsonius", "locId": "L200627", "locName": "Horseshoe Lake State Park", "obsDt": "2025-12-28 07:40", "howMany": 1, "lat": 38.7039503, "lng": -90.0724398, "obsValid": true, "obsReviewed": false, "locationPrivate": false, "subId": "S290772995"}, {"speciesCode": "merlin", "comName": "Merlin", "sciName": "Falco columbarius", "locId": "L200627", "locName": "Horseshoe Lake State Park", "obsDt": "2025-12-28 07:40", "howMany": 1, "lat": 38.7039503, "lng": -90.0724398, "obsValid": true, "obsReviewed": false, "locationPrivate": false, "subId": "S290772995"}, {"speciesCode": "eutspa", "comName": "Eurasian Tree Sparrow", "sciName": "Passer montanus", "locId": "L200627", "locName": "Horseshoe Lake State Park", "obsDt": "2025-12-28 07:40", "howMany": 1, "lat": 38.7039503, "lng": -90.0724398, "obsValid": true, "obsReviewed": false, "locationPrivate": false, "subId": "S290772995", "exoticCategory": "N"}, {"speciesCode": "amtspa", "comName": "American Tree Sparrow", "sciName": "Spizelloides arborea", "locId": "L200627", "locName": "Horseshoe Lake State Park", "obsDt": "2025-12-28 07:40", "howMany": 59, "lat": 38.7039503, "lng": -90.0724398, "obsValid": true, "obsReviewed": false, "locationPrivate": false, "subId": "S290772995"}, {"speciesCode": "whcspa", "comName": "White-crowned Sparrow", "sciName": "Zonotrichia leucophrys", "locId": "L200627", "locName": "Horseshoe Lake State Park", "obsDt": "2025-12-28 07:40", "howMany": 4, "lat": 38.7039503, "lng": -90.0724398, "obsValid": true, "obsReviewed": false, "locationPrivate": false, "subId": "S290772995"}, {"speciesCode": "sonspa", "comName": "Song Sparrow", "sciName": "Melospiza melodia", "locId": "L200627", "locName": "Horseshoe Lake State Park", "obsDt": "2025-12-28 07:40", "howMany": 2, "lat": 38.7039503, "lng": -90.0724398, "obsValid": true, "obsReviewed": false, "locationPrivate": false, "subId": "S290772995"}, {"speciesCode": "coohaw", "comName": "Cooper's Hawk", "sciName": "Astur cooperii", "locId": "L1483241", "locName": "No Name Park", "obsDt": "2025-12-28 06:33", "howMany": 1, "lat": 38.9439859, "lng": -90.1631452, "obsValid": true, "obsReviewed": false, "locationPrivate": true, "subId": "S290888450"}, {"speciesCode": "reshaw", "comName": "Red-shouldered Hawk", "sciName": "Buteo lineatus", "locId": "L1483241", "locName": "No Name Park", "obsDt": "2025-12-28 06:33", "howMany": 1, "lat": 38.9439859, "lng": -90.1631452, "obsValid": true, "obsReviewed": false, "locationPrivate": true, "subId": "S290888450"}, {"speciesCode": "rethaw", "comName": "Red-tailed Hawk", "sciName": "Buteo jamaicensis", "locId": "L1483241", "locName": "No Name Park", "obsDt": "2025-12-28 06:33", "howMany": 1, "lat": 38.9439859, "lng": -90.1631452, "obsValid": true, "obsReviewed": false, "locationPrivate": true, "subId": "S290888450"}, {"speciesCode": "grhowl", "comName": "Great Horned Owl", "sciName": "Bubo virginianus", "locId": "L1483241", "locName": "No Name Park", "obsDt": "2025-12-28 06:33", "howMany": 1, "lat": 38.9439859, "lng": -90.1631452, "obsValid": true, "obsReviewed": false, "locationPrivate": true, "subId": "S290888450"}, {"speciesCode": "yebsap", "comName": "Yellow-bellied Sapsucker", "sciName": "Sphyrapicus varius", "locId": "L1483241", "locName": "No Name Park", "obsDt": "2025-12-28 06:33", "howMany": 1, "lat": 38.9439859, "lng": -90.1631452, "obsValid": true, "obsReviewed": false, "locationPrivate": true, "subId": "S290888450"}, {"speciesCode": "rehwoo", "comName": "Red-headed Woodpecker", "sciName": "Melanerpes erythrocephalus", "locId": "L1483241", "locName": "No Name Park", "obsDt": "2025-12-28 06:33", "howMany": 1, "lat": 38.9439859, "lng": -90.1631452, "obsValid": true, "obsReviewed": false, "locationPrivate": true, "subId": "S290888450"}, {"speciesCode": "pilwoo", "comName": "Pileated Woodpecker", "sciName": "Dryocopus pileatus", "locId": "L1483241", "locName": "No Name Park", "obsDt": "2025-12-28 06:33", "howMany": 1, "lat": 38.9439859, "lng": -90.1631452, "obsValid": true, "obsReviewed": false, "locationPrivate": true, "subId": "S290888450"}, {"speciesCode": "norfli", "comName": "Northern Flicker", "sciName": "Colaptes auratus", "locId": "L1483241", "locName": "No Name Park", "obsDt": "2025-12-28 06:33", "howMany": 2, "lat": 38.9439859, "lng": -90.1631452, "obsValid": true, "obsReviewed": false, "locationPrivate": true, "subId": "S290888450"}, {"speciesCode": "bkcchi", "comName": "Black-capped Chickadee", "sciName": "Poecile atricapillus", "locId": "L1483241", "locName": "No Name Park", "obsDt": "2025-12-28 06:33", "howMany": 3, "lat": 38.9439859, "lng": -90.1631452, "obsValid": true, "obsReviewed": true, "locationPrivate": true, "subId": "S290888450"}, {"speciesCode": "ruckin", "comName": "Ruby-crowned Kinglet", "sciName": "Corthylio calendula", "locId": "L1483241", "locName": "No Name Park", "obsDt": "2025-12-28 06:33", "howMany": 1, "lat": 38.9439859, "lng": -90.1631452, "obsValid": true, "obsReviewed": false, "locationPrivate": true, "subId": "S290888450"}, {"speciesCode": "gockin", "comName": "Golden-crowned Kinglet", "sciName": "Regulus satrapa", "locId": "L1483241", "locName": "No Name Park", "obsDt": "2025-12-28 06:33", "howMany": 2, "lat": 38.9439859, "lng": -90.1631452, "obsValid": true, "obsReviewed": false, "locationPrivate": true, "subId": "S290888450"}, {"speciesCode": "rebnut", "comName": "Red-breasted Nuthatch", "sciName": "Sitta canadensis", "locId": "L1483241", "locName": "No Name Park", "obsDt": "2025-12-28 06:33", "howMany": 1, "lat": 38.9439859, "lng": -90.1631452, "obsValid": true, "obsReviewed": false, "locationPrivate": true, "subId": "S290888450"}, {"speciesCode": "eastow", "comName": "Eastern Towhee", "sciName": "Pipilo erythrophthalmus", "locId": "L1483241", "locName": "No Name Park", "obsDt": "2025-12-28 06:33", "howMany": 2, "lat": 38.9439859, "lng": -90.1631452, "obsValid": true, "obsReviewed": false, "locationPrivate": true, "subId": "S290888450"}, {"speciesCode": "bnhcow", "comName": "Brown-headed Cowbird", "sciName": "Molothrus ater", "locId": "L1483241", "locName": "No Name Park", "obsDt": "2025-12-28 06:33", "howMany": 2, "lat": 38.9439859, "lng": -90.1631452, "obsValid": true, "obsReviewed": false, "locationPrivate": true, "subId": "S290888450"}]