[{"speciesCode": "cangoo", "comName": "Canada Goose", "sciName": "Branta canadensis", "locId": "L12241078", "locName": "Caseyville", "obsDt": "2025-12-24 08:30", "howMany": 6, "lat": 38.636007, "lng": -90.018361, "obsValid": true, "obsReviewed": false, "locationPrivate": true, "subId": "S290432961"}, {"speciesCode": "moudov", "comName": "Mourning Dove", "sciName": "Zenaida macroura", "locId": "L12241078", "locName": "Caseyville", "obsDt": "2025-12-24 08:30", "howMany": 8, "lat": 38.636007, "lng": -90.018361, "obsValid": true, "obsReviewed": false, "locationPrivate": true, "subId": "S290432961"}, {"speciesCode": "coohaw", "comName": "Cooper's Hawk", "sciName": "Astur cooperii", "locId": "L12241078", "locName": "Caseyville", "obsDt": "2025-12-24 08:30", "howMany": 1, "lat": 38.636007, "lng": -90.018361, "obsValid": true, "obsReviewed": false, "locationPrivate": true, "subId": "S290432961"}, {"speciesCode": "brdowl", "comName": "Barred Owl", "sciName": "Strix varia", "locId": "L12241078", "locName": "Caseyville", "obsDt": "2025-12-24 08:30", "howMany": 2, "lat": 38.636007, "lng": -90.018361, "obsValid": true, "obsReviewed": false, "locationPrivate": true, "subId": "S290432961"}, {"speciesCode": "rebwoo", "comName": "Red-bellied Woodpecker", "sciName": "Melanerpes carolinus", "locId": "L12241078", "locName": "Caseyville", "obsDt": "2025-12-24 08:30", "howMany": 2, "lat": 38.636007, "lng": -90.018361, "obsValid": true, "obsReviewed": false, "locationPrivate": true, "subId": "S290432961"}, {"speciesCode": "dowwoo", "comName": "Downy Woodpecker", "sciName": "Dryobates pubescens", "locId": "L12241078", "locName": "Caseyville", "obsDt": "2025-12-24 08:30", "howMany": 3, "lat": 38.636007, "lng": -90.018361, "obsValid": true, "obsReviewed": false, "locationPrivate": true, "subId": "S290432961"}, {"speciesCode": "haiwoo", "comName": "Hairy Woodpecker", "sciName": "Leuconotopicus villosus", "locId": "L12241078", "locName": "Caseyville", "obsDt": "2025-12-24 08:30", "howMany": 1, "lat": 38.636007, "lng": -90.018361, "obsValid": true, "obsReviewed": false, "locationPrivate": true, "subId": "S290432961"}, {"speciesCode": "blujay", "comName": "Blue Jay", "sciName": "Cyanocitta cristata", "locId": "L12241078", "locName": "Caseyville", "obsDt": "2025-12-24 08:30", "howMany": 5, "lat": 38.636007, "lng": -90.018361, "obsValid": true, "obsReviewed": false, "locationPrivate": true, "subId": "S290432961"}, {"speciesCode": "amecro", "comName": "American Crow", "sciName": "Corvus brachyrhynchos", "locId": "L12241078", "locName": "Caseyville", "obsDt": "2025-12-24 08:30", "howMany": 2, "lat": 38.636007, "lng": -90.018361, "obsValid": true, "obsReviewed": false, "locationPrivate": true, "subId": "S290432961"}, {"speciesCode": "carchi", "comName": "Carolina Chickadee", "sciName": "Poecile carolinensis", "locId": "L12241078", "locName": "Caseyville", "obsDt": "2025-12-24 08:30", "howMany": 3, "lat": 38.636007, "lng": -90.018361, "obsValid": true, "obsReviewed": false, "locationPrivate": true, "subId": "S290432961"}, {"speciesCode": "whbnut", "comName": "White-breasted Nuthatch", "sciName": "Sitta carolinensis", "locId": "L12241078", "locName": "Caseyville", "obsDt": "2025-12-24 08:30", "howMany": 2, "lat": 38.636007, "lng": -90.018361, "obsValid": true, "obsReviewed": false, "locationPrivate": true, "subId": "S290432961"}, {"speciesCode": "winwre3", "comName": "Winter Wren", "sciName": "Troglodytes hiemalis", "locId": "L12241078", "locName": "Caseyville", "obsDt": "2025-12-24 08:30", "howMany": 1, "lat": 38.636007, "lng": -90.018361, "obsValid": true, "obsReviewed": false, "locationPrivate": true, "subId": "S290432961"}, {"speciesCode": "carwre", "comName": "Carolina Wren", "sciName": "Thryothorus ludovicianus", "locId": "L12241078", "locName": "Caseyville", "obsDt": "2025-12-24 08:30", "howMany": 2, "lat": 38.636007, "lng": -90.018361, "obsValid": true, "obsReviewed": false, "locationPrivate": true, "subId": "S290432961"}, {"speciesCode": "eursta", "comName": "European Starling", "sciName": "Sturnus vulgaris", "locId": "L12241078", "locName": "Caseyville", "obsDt": "2025-12-24 08:30", "howMany": 4, "lat": 38.636007, "lng": -90.018361, "obsValid": true, "obsReviewed": false, "locationPrivate": true, "subId": "S290432961", "exoticCategory": "N"}, {"speciesCode": "amerob", "comName": "American Robin", "sciName": "Turdus migratorius", "locId": "L12241078", "locName": "Caseyville", "obsDt": "2025-12-24 08:30", "howMany": 1, "lat": 38.636007, "lng": -90.018361, "obsValid": true, "obsReviewed": false, "locationPrivate": true, "subId": "S290432961"}, {"speciesCode": "houspa", "comName": "House Sparrow", "sciName": "Passer domesticus", "locId": "L12241078", "locName": "Caseyville", "obsDt": "2025-12-24 08:30", "howMany": 14, "lat": 38.636007, "lng": -90.018361, "obsValid": true, "obsReviewed": false, "locationPrivate": true, "subId": "S290432961", "exoticCategory": "N"}, {"speciesCode": "houfin", "comName": "House Finch", "sciName": "Haemorhous mexicanus", "locId": "L12241078", "locName": "Caseyville", "obsDt": "2025-12-24 08:30", "howMany": 3, "lat": 38.636007, "lng": -90.018361, "obsValid": true, "obsReviewed": false, "locationPrivate": true, "subId": "S290432961", "exoticCategory": "N"}, {"speciesCode": "daejun", "comName": "Dark-eyed Junco", "sciName": "Junco hyemalis", "locId": "L12241078", "locName": "Caseyville", "obsDt": "2025-12-24 08:30", "howMany": 2, "lat": 38.636007, "lng": -90.018361, "obsValid": true, "obsReviewed": false, "locationPrivate": true, "subId": "S290432961"}, {"speciesCode": "whtspa", "comName": "White-throated Sparrow", "sciName": "Zonotrichia albicollis", "locId": "L12241078", "locName": "Caseyville", "obsDt": "2025-12-24 08:30", "howMany": 2, "lat": 38.636007, "lng": -90.018361, "obsValid": true, "obsReviewed": false, "locationPrivate": true, "subId": "S290432961"}, {"speciesCode": "rewbla", "comName": "Red-winged Blackbird", "sciName": "Agelaius phoeniceus", "locId": "L12241078", "locName": "Caseyville", "obsDt": "2025-12-24 08:30", "howMany": 1, "lat": 38.636007, "lng": -90.018361, "obsValid": true, "obsReviewed": false, "locationPrivate": true, "subId": "S290432961"}, {"speciesCode": "comgra", "comName": "Common Grackle", "sciName": "Quiscalus quiscula", "locId": "L12241078", "locName": "Caseyville", "obsDt": "2025-12-24 08:30", "howMany": 1, "lat": 38.636007, "lng": -90.018361, "obsValid": true, "obsReviewed": false, "locationPrivate": true, "subId": "S290432961"}, {"speciesCode": "norcar", "comName": "Northern Cardinal", "sciName": "Cardinalis cardinalis", "locId": "L12241078", "locName": "Caseyville", "obsDt": "2025-12-24 08:30", "howMany": 18, "lat": 38.636007, "lng": -90.018361, "obsValid": true, "obsReviewed": false, "locationPrivate": true, "subId": "S290432961"}, {"speciesCode": "mallar3", "comName": "Mallard", "sciName": "Anas platyrhynchos", "locId": "L37403805", "locName": "215 Luca James Point, O'Fallon, Illinois, US (38.634, -89.919)", "obsDt": "2025-12-24 07:50", "howMany": 2, "lat": 38.633868, "lng": -89.9191041, "obsValid": true, "obsReviewed": false, "locationPrivate": true, "subId": "S289991519"}, {"speciesCode": "grbher3", "comName": "Great Blue Heron", "sciName": "Ardea herodias", "locId": "L37403805", "locName": "215 Luca James Point, O'Fallon, Illinois, US (38.634, -89.919)", "obsDt": "2025-12-24 07:50", "howMany": 1, "lat": 38.633868, "lng": -89.9191041, "obsValid": true, "obsReviewed": false, "locationPrivate": true, "subId": "S289991519"}, {"speciesCode": "reshaw", "comName": "Red-shouldered Hawk", "sciName": "Buteo lineatus", "locId": "L37403805", "locName": "215 Luca James Point, O'Fallon, Illinois, US (38.634, -89.919)", "obsDt": "2025-12-24 07:50", "howMany": 2, "lat": 38.633868, "lng": -89.9191041, "obsValid": true, "obsReviewed": false, "locationPrivate": true, "subId": "S289991519"}, {"speciesCode": "rethaw", "comName": "Red-tailed Hawk", "sciName": "Buteo jamaicensis", "locId": "L37403805", "locName": "215 Luca James Point, O'Fallon, Illinois, US (38.634, -89.919)", "obsDt": "2025-12-24 07:50", "howMany": 1, "lat": 38.633868, "lng": -89.9191041, "obsValid": true, "obsReviewed": false, "locationPrivate": true, "subId": "S289991519"}, {"speciesCode": "grhowl", "comName": "Great Horned Owl", "sciName": "Bubo virginianus", "locId": "L37403805", "locName": "215 Luca James Point, O'Fallon, Illinois, US (38.634, -89.919)", "obsDt": "2025-12-24 07:50", "howMany": 1, "lat": 38.633868, "lng": -89.9191041, "obsValid": true, "obsReviewed": false, "locationPrivate": true, "subId": "S289991519"}, {"speciesCode": "yebsap", "comName": "Yellow-bellied Sapsucker", "sciName": "Sphyrapicus varius", "locId": "L37403805", "locName": "215 Luca James Point, O'Fallon, Illinois, US (38.634, -89.919)", "obsDt": "2025-12-24 07:50", "howMany": 1, "lat": 38.633868, "lng": -89.9191041, "obsValid": true, "obsReviewed": false, "locationPrivate": true, "subId": "S289991519"}, {"speciesCode": "rehwoo", "comName": "Red-headed Woodpecker", "sciName": "Melanerpes erythrocephalus", "locId": "L37403805", "locName": "215 Luca James Point, O'Fallon, Illinois, US (38.634, -89.919)", "obsDt": "2025-12-24 07:50", "howMany": 1, "lat": 38.633868, "lng": -89.9191041, "obsValid": true, "obsReviewed": false, "locationPrivate": true, "subId": "S289991519"}, {"speciesCode": "pilwoo", "comName": "Pileated Woodpecker", "sciName": "Dryocopus pileatus", "locId": "L37403805", "locName": "215 Luca James Point, O'Fallon, Illinois, US (38.634, -89.919)", "obsDt": "2025-12-24 07:50", "howMany": 2, "lat": 38.633868, "lng": -89.9191041, "obsValid": true, "obsReviewed": false, "locationPrivate": true, "subId": "S289991519"}, {"speciesCode": "norfli", "comName": "Northern Flicker", "sciName": "Colaptes auratus", "locId": "L37403805", "locName": "215 Luca James Point, O'Fallon, Illinois, US (38.634, -89.919)", "obsDt": "2025-12-24 07:50", "howMany": 2, "lat": 38.633868, "lng": -89.9191041, "obsValid": true, "obsReviewed": false, "locationPrivate": true, "subId": "S289991519"}, {"speciesCode": "tuftit", "comName": "Tufted Titmouse", "sciName": "Baeolophus bicolor", "locId": "L37403805", "locName": "215 Luca James Point, O'Fallon, Illinois, US (38.634, -89.919)", "obsDt": "2025-12-24 07:50", "howMany": 13, "lat": 38.633868, "lng": -89.9191041, "obsValid": true, "obsReviewed": false, "locationPrivate": true, "subId": "S289991519"}, {"speciesCode": "gockin", "comName": "Golden-crowned Kinglet", "sciName": "Regulus satrapa", "locId": "L37403805", "locName": "215 Luca James Point, O'Fallon, Illinois, US (38.634, -89.919)", "obsDt": "2025-12-24 07:50", "howMany": 2, "lat": 38.633868, "lng": -89.9191041, "obsValid": true, "obsReviewed": false, "locationPrivate": true, "subId": "S289991519"}, {"speciesCode": "easblu", "comName": "Eastern Bluebird", "sciName": "Sialia sialis", "locId": "L37403805", "locName": "215 Luca James Point, O'Fallon, Illinois, US (38.634, -89.919)", "obsDt": "2025-12-24 07:50", "howMany": 6, "lat": 38.633868, "lng": -89.9191041, "obsValid": true, "obsReviewed": false, "locationPrivate": true, "subId": "S289991519"}, {"speciesCode": "herthr", "comName": "Hermit Thrush", "sciName": "Catharus guttatus", "locId": "L37403805", "locName": "215 Luca James Point, O'Fallon, Illinois, US (38.634, -89.919)", "obsDt": "2025-12-24 07:50", "howMany": 1, "lat": 38.633868, "lng": -89.9191041, "obsValid": true, "obsReviewed": false, "locationPrivate": true, "subId": "S289991519"}, {"speciesCode": "pinsis", "comName": "Pine Siskin", "sciName": "Spinus pinus", "locId": "L37403805", "locName": "215 Luca James Point, O'Fallon, Illinois, US (38.634, -89.919)", "obsDt": "2025-12-24 07:50", "howMany": 1, "lat": 38.633868, "lng": -89.9191041, "obsValid": true, "obsReviewed": false, "locationPrivate": true, "subId": "S289991519"}, {"speciesCode": "amegfi", "comName": "American Goldfinch", "sciName": "Spinus tristis", "locId": "L37403805", "locName": "215 Luca James Point, O'Fallon, Illinois, US (38.634, -89.919)", "obsDt": "2025-12-24 07:50", "howMany": 12, "lat": 38.633868, "lng": -89.9191041, "obsValid": true, "obsReviewed": false, "locationPrivate": true, "subId": "S289991519"}, {"speciesCode": "bnhcow", "comName": "Brown-headed Cowbird", "sciName": "Molothrus ater", "locId": "L37403805", "locName": "215 Luca James Point, O'Fallon, Illinois, US (38.634, -89.919)", "obsDt": "2025-12-24 07:50", "howMany": 7, "lat": 38.633868, "lng": -89.9191041, "obsValid": true, "obsReviewed": false, "locationPrivate": true, "subId": "S289991519"}, {"speciesCode": "rusbla", "comName": "Rusty Blackbird", "sciName": "Euphagus carolinus", "locId": "L37403805", "locName": "215 Luca James Point, O'Fallon, Illinois, US (38.634, -89.919)", "obsDt": "2025-12-24 07:50", "howMany": 1, "lat": 38.633868, "lng": -89.9191041, "obsValid": true, "obsReviewed": false, "locationPrivate": true, "subId": "S289991519"}, {"speciesCode": "yerwar", "comName": "Yellow-rumped Warbler", "sciName": "Setophaga coronata", "locId": "L37403805", "locName": "215 Luca James Point, O'Fallon, Illinois, US (38.634, -89.919)", "obsDt": "2025-12-24 07:50", "howMany": 2, "lat": 38.633868, "lng": -89.9191041, "obsValid": true, "obsReviewed": false, "locationPrivate": true, "subId": "S289991519"}]